{
  "schemaVersion": 1,
  "id": "railtransportplus",
  "version": "${version}",

  "name": "Rail Transport Plus",
  "description": "Adds linkable minecarts and faster than default minecart top speed.",
  "authors": [
    "antD97"
  ],
  "contact": {
    "homepage": "https://github.com/antD97/RailTransportPlus",
    "issues": "https://github.com/antD97/RailTransportPlus/issues",
    "sources": "https://github.com/antD97/RailTransportPlus"
  },

  "license": "MIT",
  "icon": "assets/railtransportplus/icon.png",

  "environment": "*",
  "entrypoints": {
    "main": [
      "com.antd.railtransportplus.RailTransportPlus"
    ],
    "client": [
      "com.antd.railtransportplus.RailTransportPlusClient"
    ]
  },
  "mixins": [
    "railtransportplus.mixins.json"
  ],

  "depends": {
    "fabricloader": ">=0.15.1",
    "fabric-api": ">=0.83.0",
    "minecraft": "1.20",
    "java": ">=17"
  }
}
